procmodeling/__init__.py
procmodeling/solver/__init__.py
procmodeling/solver/edo_functions.py
procmodeling/solver/utils/__init__.py
procmodeling/solver/utils/_expressionlist_2_latex.py
procmodeling/solver/utils/_find_and_replace_expression.py
procmodeling/solver/utils/_is_number.py
procmodeling/solver/utils/_plot_text.py
procmodeling-1.0.0.dist-info/LICENSE
procmodeling-1.0.0.dist-info/METADATA
procmodeling-1.0.0.dist-info/WHEEL
procmodeling-1.0.0.dist-info/top_level.txt
procmodeling-1.0.0.dist-info/RECORD
