Metadata-Version: 2.1
Name: procmodeling
Version: 1.0.0
Home-page: https://github.com/tenoriolms/procmodeling_lib
Author: tenoriolms
Classifier: Programming Language :: Python :: 3
Classifier: License :: OSI Approved :: BSD License
Classifier: Operating System :: OS Independent
Requires-Python: >=3.6
License-File: LICENSE
Requires-Dist: numpy >=2.2.4
Requires-Dist: pandas >=2.2.3
Requires-Dist: matplotlib >=3.10.1
Requires-Dist: scipy >=1.15.2
Requires-Dist: sympy >=1.13.3
